[{"id":1,"first_name":"Christos","last_name":"Kirkbright","email":"ckirkbright0@gnu.org","gender":"Male"},
{"id":2,"first_name":"Mercy","last_name":"Reding","email":"mreding1@privacy.gov.au","gender":"Female"},
{"id":3,"first_name":"Dehlia","last_name":"Greenrodd","email":"dgreenrodd2@sakura.ne.jp","gender":"Female"},
{"id":4,"first_name":"Kristal","last_name":"Unitt","email":"kunitt3@usatoday.com","gender":"Female"},
{"id":5,"first_name":"Jilly","last_name":"Serridge","email":"jserridge4@europa.eu","gender":"Female"},
{"id":6,"first_name":"Tarrah","last_name":"MacAndie","email":"tmacandie5@ibm.com","gender":"Female"},
{"id":7,"first_name":"Pip","last_name":"Rollason","email":"prollason6@mozilla.org","gender":"Male"},
{"id":8,"first_name":"Legra","last_name":"Clinning","email":"lclinning7@addthis.com","gender":"Female"},
{"id":9,"first_name":"Haily","last_name":"Crawcour","email":"hcrawcour8@weebly.com","gender":"Female"},
{"id":10,"first_name":"Alexi","last_name":"Lidgely","email":"alidgely9@twitter.com","gender":"Female"},
{"id":11,"first_name":"Shawnee","last_name":"Aldiss","email":"saldissa@meetup.com","gender":"Female"},
{"id":12,"first_name":"Madelle","last_name":"Twopenny","email":"mtwopennyb@cpanel.net","gender":"Female"},
{"id":13,"first_name":"Dewitt","last_name":"Slocomb","email":"dslocombc@timesonline.co.uk","gender":"Male"},
{"id":14,"first_name":"Noach","last_name":"Hayden","email":"nhaydend@behance.net","gender":"Male"},
{"id":15,"first_name":"Elnora","last_name":"Astbery","email":"eastberye@google.com.br","gender":"Female"},
{"id":16,"first_name":"Marketa","last_name":"Medcalfe","email":"mmedcalfef@google.it","gender":"Female"},
{"id":17,"first_name":"Artemas","last_name":"Dudenie","email":"adudenieg@wordpress.com","gender":"Male"},
{"id":18,"first_name":"Lori","last_name":"Harniman","email":"lharnimanh@51.la","gender":"Female"},
{"id":19,"first_name":"Augy","last_name":"Turneux","email":"aturneuxi@wisc.edu","gender":"Male"},
{"id":20,"first_name":"Giacopo","last_name":"Rahl","email":"grahlj@imageshack.us","gender":"Male"},
{"id":21,"first_name":"Fairleigh","last_name":"Kenset","email":"fkensetk@omniture.com","gender":"Male"},
{"id":22,"first_name":"Erhart","last_name":"Mizzen","email":"emizzenl@alibaba.com","gender":"Male"},
{"id":23,"first_name":"Parsifal","last_name":"Downie","email":"pdowniem@phoca.cz","gender":"Male"},
{"id":24,"first_name":"Andy","last_name":"Feldbau","email":"afeldbaun@ning.com","gender":"Male"},
{"id":25,"first_name":"Orland","last_name":"Cossor","email":"ocossoro@bbc.co.uk","gender":"Male"},
{"id":26,"first_name":"Orv","last_name":"Flippelli","email":"oflippellip@admin.ch","gender":"Male"},
{"id":27,"first_name":"Fredek","last_name":"Havard","email":"fhavardq@sun.com","gender":"Male"},
{"id":28,"first_name":"Laraine","last_name":"Garralts","email":"lgarraltsr@meetup.com","gender":"Female"},
{"id":29,"first_name":"Ingrim","last_name":"Flann","email":"iflanns@squarespace.com","gender":"Male"},
{"id":30,"first_name":"Richard","last_name":"Samudio","email":"rsamudiot@nbcnews.com","gender":"Male"},
{"id":31,"first_name":"Haroun","last_name":"Horsey","email":"hhorseyu@amazon.de","gender":"Male"},
{"id":32,"first_name":"Daune","last_name":"Saturley","email":"dsaturleyv@blogs.com","gender":"Female"},
{"id":33,"first_name":"Anissa","last_name":"Gwatkin","email":"agwatkinw@cornell.edu","gender":"Female"},
{"id":34,"first_name":"Jule","last_name":"Beswell","email":"jbeswellx@zdnet.com","gender":"Male"},
{"id":35,"first_name":"Earl","last_name":"McEneny","email":"emcenenyy@livejournal.com","gender":"Male"},
{"id":36,"first_name":"Jaime","last_name":"Porcas","email":"jporcasz@vkontakte.ru","gender":"Female"},
{"id":37,"first_name":"Christiane","last_name":"Salvador","email":"csalvador10@cbc.ca","gender":"Female"},
{"id":38,"first_name":"Judas","last_name":"Wiffler","email":"jwiffler11@soup.io","gender":"Male"},
{"id":39,"first_name":"Linette","last_name":"Hillen","email":"lhillen12@springer.com","gender":"Female"},
{"id":40,"first_name":"Gery","last_name":"Silby","email":"gsilby13@flavors.me","gender":"Male"},
{"id":41,"first_name":"Trista","last_name":"Moubray","email":"tmoubray14@diigo.com","gender":"Female"},
{"id":42,"first_name":"Farleigh","last_name":"Warder","email":"fwarder15@weibo.com","gender":"Male"},
{"id":43,"first_name":"Stevy","last_name":"Stainsby","email":"sstainsby16@alexa.com","gender":"Male"},
{"id":44,"first_name":"Galvin","last_name":"Somerfield","email":"gsomerfield17@hugedomains.com","gender":"Male"},
{"id":45,"first_name":"Rozamond","last_name":"Chisolm","email":"rchisolm18@com.com","gender":"Female"},
{"id":46,"first_name":"Crista","last_name":"Ponte","email":"cponte19@lulu.com","gender":"Female"},
{"id":47,"first_name":"Nicolai","last_name":"Parell","email":"nparell1a@sitemeter.com","gender":"Male"},
{"id":48,"first_name":"Ginny","last_name":"MacAlpin","email":"gmacalpin1b@psu.edu","gender":"Female"},
{"id":49,"first_name":"Abigale","last_name":"Ordish","email":"aordish1c@free.fr","gender":"Female"},
{"id":50,"first_name":"Natalee","last_name":"Kulicke","email":"nkulicke1d@nasa.gov","gender":"Female"}]